README.rst
setup.cfg
setup.py
mopyx/__init__.py
mopyx/models.py
mopyx/rendering.py
mopyx/util.py
mopyx.egg-info/PKG-INFO
mopyx.egg-info/SOURCES.txt
mopyx.egg-info/dependency_links.txt
mopyx.egg-info/top_level.txt
test/__init__.py
test/test_action_on_model.py
test/test_computed_first_in_render.py
test/test_computed_property.py
test/test_ignore_updates.py
test/test_inheritance.py
test/test_list_render.py
test/test_merge_model.py
test/test_nested_lists_render.py
test/test_nested_render.py
test/test_render.py
test/test_serialization.py