Metadata-Version: 1.0
Name: mopyx
Version: 1.1.1
Summary: mopyx
Home-page: UNKNOWN
Author: Bogdan Mustiata
Author-email: bogdan.mustiata@gmail.com
License: BSD
Platform: UNKNOWN
